{
    "status": "ok",
    "totalResults": 351,
    "articles": [
        {
            "source": {
                "id": null,
                "name": "Hipertextual"
            },
            "author": "Quelian Sanz",
            "title": "El iPhone 17 Pro sí que podría ser una revolución: se han filtrado detalles de su cámara que te van a encantar",
            "description": "Un informante anónimo acaba de revolucionar todo lo que creíamos sobre el iPhone 17 Pro. No sobre su diseño, pantalla o precio, sino sobre la cámara que incluirá el modelo más avanzado de la nueva serie. Todo parecía tranquilo en este sentido y no se esperaba…",
            "url": "http://hipertextual.com/apple/el-iphone-17-pro-si-que-podria-ser-una-revolucion-se-han-filtrado-detalles-de-su-camara-que-te-van-a-encantar/",
            "urlToImage": "https://imgs.hipertextual.com/wp-content/uploads/2025/07/iphone-17.jpg",
            "publishedAt": "2025-07-28T07:23:20Z",
            "content": "Un informante anónimo acaba de revolucionar todo lo que creíamos sobre el iPhone 17 Pro. No sobre su diseño, pantalla o precio, sino sobre la cámara que incluirá el modelo más avanzado de la nueva se… [+3500 chars]"
        },
        {
            "source": {
                "id": null,
                "name": "Yahoo Entertainment"
            },
            "author": "Ankur Banerjee",
            "title": "Stocks cheer the art of Trump's trade deals after EU agreement",
            "description": "SINGAPORE (Reuters) -Global stocks rose and the euro firmed on Monday after a trade agreement between the United States and the EU lifted sentiment and...",
            "url": "https://finance.yahoo.com/news/stocks-cheer-art-trumps-trade-011627968.html",
            "urlToImage": "https://media.zenfs.com/en/reuters-finance.com/d29708ea14fd3ea96d6d6778a975ae1f",
            "publishedAt": "2025-07-28T01:16:27Z",
            "content": "By Ankur Banerjee\r\nSINGAPORE (Reuters) -Global stocks rose and the euro firmed on Monday after a trade agreement between the United States and the EU lifted sentiment and provided clarity in a pivota… [+3517 chars]"
        },
        {
            "source": {
                "id": null,
                "name": "heise online"
            },
            "author": "Ben Schwan",
            "title": "Apple TV+: Mit \"Prestige-Fernsehen\" zum neuen HBO?",
            "description": "Apple scheint sich den Aufstieg eines US-Kabel-TV-Senders als Vorbild für seinen Streamingdienst ausgeguckt zu haben. Die Kritik gibt dem Dienst recht.",
            "url": "https://www.heise.de/news/Apple-TV-Mit-Prestige-Fernsehen-zum-neuen-HBO-10498526.html",
            "urlToImage": "https://heise.cloudimg.io/bound/1200x1200/q85.png-lossy-85.webp-lossy-85.foil1/_www-heise-de_/imgs/18/4/9/0/3/2/8/3/Screenshot_2025-07-24_at_15.00.06-3bb141e2337a860b.png",
            "publishedAt": "2025-07-28T08:38:00Z",
            "content": "close notice\r\nThis article is also available in\r\n English.\r\nIt was translated with technical assistance and editorially reviewed before publication.\r\nDont show this again.\r\nApples Streamingdienst TV+… [+2639 chars]"
        },
        {
            "source": {
                "id": null,
                "name": "heise online"
            },
            "author": "Frank Schräer",
            "title": "Montag: Datenraub bei Allianz in den USA, Einigung von EU und USA im Zollstreit",
            "description": "Cyberangriff auf Allanz Life + Zollabkommen der EU mit Trump + Google verwirft goo.gl + Schadenersatz nach Street-View-Nacktbild + Apples zweigeteilte Welt",
            "url": "https://www.heise.de/news/Montag-Datenraub-bei-Allianz-in-den-USA-Einigung-von-EU-und-USA-im-Zollstreit-10501134.html",
            "urlToImage": "https://heise.cloudimg.io/bound/1200x1200/q85.png-lossy-85.webp-lossy-85.foil1/_www-heise-de_/imgs/18/4/9/0/4/6/2/6/monday-e768acdef0ccedf5.webp",
            "publishedAt": "2025-07-28T04:15:00Z",
            "content": "Die US-Lebensversicherung Allianz Life bestätigte einen Cyberangriff auf eine Datenbank mit persönlichen Daten der meisten Kunden. Nach Unternehmensangaben konnten sich die Angreifer durch Social-Eng… [+4660 chars]"
        },
        {
            "source": {
                "id": null,
                "name": "Applesfera.com"
            },
            "author": "Álvaro García M.",
            "title": "Soy fan de 'Ted Lasso' y tengo un problema: no sé si quiero que la serie continue. Y Apple parece tenerlo claro",
            "description": "La serie de más exito de Apple TV+ está de vuelta. O casi. La cuarta temporada de 'Ted Lasso' se empezó a rodar la semana pasada y debido a ello no se espera su estreno hasta el año que viene como mínimo. Sin embargo, ya se han ido avanzando detalles de la tr…",
            "url": "https://www.applesfera.com/servicios-apple/soy-fan-ted-lasso-tengo-problema-no-se-quiero-que-serie-continue-apple-parece-tenerlo-claro",
            "urlToImage": "https://i.blogs.es/d36b7c/ted-lasso/840_560.jpeg",
            "publishedAt": "2025-07-28T08:28:48Z",
            "content": "La serie de más exito de Apple TV+ está de vuelta. O casi. La cuarta temporada de 'Ted Lasso' se empezó a rodar la semana pasada y debido a ello no se espera su estreno hasta el año que viene como mí… [+3607 chars]"
        },
        {
            "source": {
                "id": null,
                "name": "Applesfera.com"
            },
            "author": "Álvaro García M.",
            "title": "Pocas veces me ha emocionado tanto una cámara como la del iPhone 17 Pro. Se acaban de filtrar sus tres grandes novedades",
            "description": "Apple no ha presentado aún los iPhone 17 y ni falta que hace si queremos saber qué novedades traerá. Están ya a punto de entrar en producción (si es que no lo han hecho ya) y hay cada vez más filtraciones y más fiables. La última responde a lo que podemos esp…",
            "url": "https://www.applesfera.com/rumores/pocas-veces-me-ha-emocionado-camara-como-iphone-17-pro-se-acaban-filtrar-sus-tres-grandes-novedades",
            "urlToImage": "https://i.blogs.es/63e11a/iphone-17-proc/840_560.jpeg",
            "publishedAt": "2025-07-28T07:00:29Z",
            "content": "Apple no ha presentado aún los iPhone 17 y ni falta que hace si queremos saber qué novedades traerá. Están ya a punto de entrar en producción (si es que no lo han hecho ya) y hay cada vez más filtrac… [+2364 chars]"
        },
        {
            "source": {
                "id": null,
                "name": "Phandroid - News for Android"
            },
            "author": "Tyler Lee",
            "title": "iPhone 17 Pro telephoto zoom could outclass Galaxy S26 Ultra",
            "description": "The iPhone 17 Pro telephoto zoom may reach 8x with a moving lens, making it a serious rival to Samsung's best. Here's what the rumor says.\nThe post iPhone 17 Pro telephoto zoom could outclass Galaxy S26 Ultra appeared first on Phandroid.",
            "url": "https://phandroid.com/2025/07/28/iphone-17-pro-telephoto-zoom-could-outclass-galaxy-s26-ultra/",
            "urlToImage": "https://phandroid.com/wp-content/uploads/2024/09/iphone-16-3-1.png",
            "publishedAt": "2025-07-28T08:48:58Z",
            "content": "The iPhone 17 Pro telephoto zoom might finally give Apple the upper hand in long-range photography. A new leak suggests the phone will offer 8x optical zoom with a moving lens, up from 5x on the iPho… [+1263 chars]"
        },
        {
            "source": {
                "id": null,
                "name": "Presse-citron"
            },
            "author": "Setra",
            "title": "Il sera (très) difficile de résister à l’appareil photo de l’iPhone 17 Pro",
            "description": "Apple aurait prévu d’importantes améliorations pour l’appareil photo de l’iPhone 17 Pro, ainsi qu’une application “pro” pour offrir encore plus de fonctionnalités.",
            "url": "https://www.presse-citron.net/il-sera-tres-difficile-de-resister-a-lappareil-photo-de-liphone-17-pro/",
            "urlToImage": "https://www.presse-citron.net/app/uploads/2025/06/Apple-logo-1-1600x900.jpg",
            "publishedAt": "2025-07-28T09:01:30Z",
            "content": "Apple est peut-être en retard dans la course à lIA, mais celui-ci continue dexceller dans certains domaines, comme la photographie sur mobile. Et normalement, liPhone 17 Pro et liPhone 17 Pro Max, qu… [+2346 chars]"
        },
        {
            "source": {
                "id": null,
                "name": "Habr.com"
            },
            "author": "Suvitruf",
            "title": "Недельный геймдев: #236 — 27 июля, 2025",
            "description": "Из новостей: Deltarune стала самой продаваемой игрой в eShop, с платформы itchio удалили тысячи игр для взрослых, суд отказал авторам The Day Before в удовлетворении иска, умер Джулиан ЛеФэй — «отец The Elder Scrolls».Из интересностей: Godot Pixel Renderer, к…",
            "url": "https://habr.com/ru/articles/931590/#post-content-body",
            "urlToImage": "https://habrastorage.org/getpro/habr/upload_files/35f/186/2d1/35f1862d1e2a56465d5b854e8c4cd321.jpeg",
            "publishedAt": "2025-07-28T08:22:49Z",
            "content": ": Deltarune eShop, itchio , The Day Before , « The Elder Scrolls».\r\n : Godot Pixel Renderer, Crysis, AI--, Clair Obscur: Expedition 33.\r\n//\r\nDeltarune eShop Switch 2\r\nNewzoo , eShop, Switch 2: 5 . : … [+2051 chars]"
        },
        {
            "source": {
                "id": null,
                "name": "CNET"
            },
            "author": "Alex Valdes （CNET News） 翻訳校正： 編集部",
            "title": "アップル、iPhoneアプリの年齢制限を強化--その背景とは？",
            "description": "アップルは、「App Store」で公開されるアプリの年齢区分に「13歳以上」「16歳以上」「18歳以上」を追加した。",
            "url": "https://japan.cnet.com/article/35235983/",
            "urlToImage": "https://japan.cnet.com/storage/2025/07/28/f06424d943e8aee23021e32a29f93af4/apple-pride-collection-hero_1280x960.jpg",
            "publishedAt": "2025-07-28T02:30:00Z",
            "content": "AppleApp Store131618121749iPhoneiPadMacBookApple WatchApple TVApple Vision Pro\r\nAppleiOS 26iPadOS 26macOS Tahoe 26tvOS 26visionOS 26watchOS 26Apple\r\nApple2Helping Protect Kids Online\r\nSekuvaForbes202… [+148 chars]"
        },
        {
            "source": {
                "id": null,
                "name": "CNET"
            },
            "author": "Abrar Al-Heeti （CNET News） 翻訳校正： 編集部",
            "title": "iPhone 17を待つべき？現時点のうわさでiPhone 16と比べてみた",
            "description": "あなたは新しい「iPhone」を買う準備ができている。選択肢は2つだ。今すぐiPhone 16を買うか、もう少し待って、約1カ月余りで登場するであろう次期モデルを手に入れるか。どちらが賢明だろうか。",
            "url": "https://japan.cnet.com/article/35235977/",
            "urlToImage": "https://japan.cnet.com/storage/2025/07/28/3bc8251fab30329e2b9b3d3d194836bd/apple-iphone-16-3086_1280x960.jpg",
            "publishedAt": "2025-07-28T03:10:00Z",
            "content": "iPhone2iPhone 161\r\n9iPhone 17iPhone 16AppleiPhone 17iPhone 16\r\niPhone 16 vs. iPhone 17\r\niPhone 17ProAirGalaxy S25 EdgeiPhone 17iPhone 17\r\n1iPhone 17120HzProPlus60Hz\r\niPhone 17iPhone 17 ProPro MaxAiri… [+576 chars]"
        },
        {
            "source": {
                "id": null,
                "name": "Omgubuntu.co.uk"
            },
            "author": "Joey Sneddon",
            "title": "Linux 6.16 Released with OpenVPN Speed Boost, 5-Level Paging + More",
            "description": "Linux 6.16 improves OpenVPN speeds, expands 5-level paging, and delivers a 'stupendous' Ext4 performance boost - and a fair bit more. Highlights inside.\nYou're reading Linux 6.16 Released with OpenVPN Speed Boost, 5-Level Paging + More, a blog post from OMG! …",
            "url": "https://www.omgubuntu.co.uk/2025/07/linux-6-16-released-openvpn-speed-boost-5-level-paging",
            "urlToImage": "https://www.omgubuntu.co.uk/wp-content/uploads/2025/07/linux-6.16.jpg",
            "publishedAt": "2025-07-28T02:12:11Z",
            "content": "The Linux 6.16 kernel is officially out, bringing a host of improvements across networking, security, and hardware support that future versions of Ubuntu will benefit from.\r\nWhy the forward-looking p… [+6582 chars]"
        },
        {
            "source": {
                "id": null,
                "name": "Caschys Blog"
            },
            "author": "caschy",
            "title": "Apple sagt dem Launchpad Lebewohl: Open-Source-Alternative LaunchBack erschienen",
            "description": "Während Apple mit macOS 26 Tahoe das seit Mac OS X 10.7 Lion bekannte Launchpad zu Grabe trägt, springt die Open-Source-Community in die Bresche. Ein Entwickler hat mit LaunchBack eine Alternative vorgestellt, die das vertraute Konzept des App-Launchers weite…",
            "url": "https://stadt-bremerhaven.de/apple-sagt-dem-launchpad-lebewohl-open-source-alternative-launchback-erschienen/",
            "urlToImage": "https://stadt-bremerhaven.de/wp-content/uploads/2025/07/458197200-1282da0a-730d-454e-9541-09cea0a1c23a.jpg",
            "publishedAt": "2025-07-28T09:30:05Z",
            "content": "Während Apple mit macOS 26 Tahoe das seit Mac OS X 10.7 Lion bekannte Launchpad zu Grabe trägt, springt die Open-Source-Community in die Bresche. Ein Entwickler hat mit LaunchBack eine Alternative vo… [+1383 chars]"
        },
        {
            "source": {
                "id": null,
                "name": "Caschys Blog"
            },
            "author": "Olli",
            "title": "iPhone 17 Pro: Gerüchte um 8-fach-Zoom, neue Pro-Kamera-App und mehr",
            "description": "Im September wird wohl das neue iPhone 17 und 17 Pro erscheinen. Zum Pro-Modell gibt es mal wieder ein paar Gerüchte. Ein anonymer Tippgeber von MacRumors berichtet, dass Apple für die Pro-Modelle unter anderem ein Teleobjektiv mit bis zu 8-fachem...Zum Beitr…",
            "url": "https://stadt-bremerhaven.de/iphone-17-pro-geruechte-um-8-fach-zoom-neue-pro-kamera-app-und-mehr/",
            "urlToImage": "https://stadt-bremerhaven.de/wp-content/uploads/2024/10/iPhone-16-Modelle-4.jpg",
            "publishedAt": "2025-07-28T04:30:21Z",
            "content": "Im September wird wohl das neue iPhone 17 und 17 Pro erscheinen. Zum Pro-Modell gibt es mal wieder ein paar Gerüchte. Ein anonymer Tippgeber von MacRumors berichtet, dass Apple für die Pro-Modelle un… [+1873 chars]"
        },
        {
            "source": {
                "id": null,
                "name": "Frandroid"
            },
            "author": "Yann Lethuillier",
            "title": "La face cachée de l’industrie auto : pourquoi les constructeurs livrent de plus en plus de voitures non finies aux clients",
            "description": "Des voitures électriques (parfois chinoises, mais pas uniquement) sont livrées en Europe avec des fonctions manquantes, voire même des bugs logiciels ou des mauvaises traductions. L'idée : livrer des voitures non finies aux clients, et compter sur les mises à…",
            "url": "https://www.frandroid.com/survoltes/voitures-electriques/2736719_la-face-cachee-de-lindustrie-auto-pourquoi-les-constructeurs-livrent-de-plus-en-plus-de-voitures-non-finies-aux-clients",
            "urlToImage": "https://c0.lestechnophiles.com/images.frandroid.com/wp-content/uploads/2025/07/hyundai-motor-group-s-pleos-software-brand.jpg?resize=1600,900&key=2fd83bb2&watermark",
            "publishedAt": "2025-07-28T05:45:00Z",
            "content": "Des voitures électriques (parfois chinoises, mais pas uniquement) sont livrées en Europe avec des fonctions manquantes, voire même des bugs logiciels ou des mauvaises traductions. L’idée : livrer des… [+11758 chars]"
        },
        {
            "source": {
                "id": null,
                "name": "Lifehacker.ru"
            },
            "author": "Евгений Лазовский",
            "title": "iPhone 17 Pro может получить продвинутое приложение-камеру и 8‑кратный оптический зум",
            "description": "Также iPhone 17 Pro, по словам инсайдера, получит дополнительную кнопку управления камерой на верхней грани.",
            "url": "https://lifehacker.ru/iphone-17-pro-mozhet-poluchit-prodvinutoe-prilozhenie-kameru/",
            "urlToImage": "https://cdn.lifehacker.ru/wp-content/uploads/2025/07/tipster_iphone_17_pro_to_feature_kopiya_upscayl_4x_remacri_4x_1753685185_scaled.jpg",
            "publishedAt": "2025-07-28T06:50:24Z",
            "content": ", iPhone 17 Pro, , . -, . Halide, Kino Filmic Pro. , , Final Cut Camera.\r\niPhone 16 Pro . , .\r\n iPhone 17 Pro, , . , iPhone 16.\r\n Apple. , 48- , - Apple , iPhone .\r\n . , iPhone ."
        },
        {
            "source": {
                "id": null,
                "name": "Puromarketing.com"
            },
            "author": null,
            "title": "¿Ha puesto la revolución de la IA en evidencia la innovación de Apple y su modelo de negocio a largo plazo?",
            "description": "La conversación sobre el rumbo estratégico de Apple en el ámbito de la Inteligencia Artificial continúa en el sector tecnológico, con un escrutinio constante sobre su capacidad para igualar el ritmo de sus competidores. Recientes especulaciones sugieren una p…",
            "url": "https://www.puromarketing.com/14/215861/puesto-revolucion-evidencia-innovacion-apple-modelo-negocio-largo-plazo",
            "urlToImage": "https://www.puromarketing.com/uploads/img/contents/2025/JM9eyvfHUjGiXuV1rmCd/JM9eyvfHUjGiXuV1rmCd_post_imagen_prev.jpg",
            "publishedAt": "2025-07-28T05:50:28Z",
            "content": "La conversación sobre el rumbo estratégico de Apple en el ámbito de la Inteligencia Artificial continúa en el sector tecnológico, con un escrutinio constante sobre su capacidad para igualar el ritmo … [+7378 chars]"
        },
        {
            "source": {
                "id": null,
                "name": "Hamusoku.com"
            },
            "author": "hamusoku",
            "title": "Mrs. GREEN APPLEさん炎上　騒音公害をまき散らし警察に通報されまくる",
            "description": "",
            "url": "https://hamusoku.com/archives/10907746.html",
            "urlToImage": "https://livedoor.blogimg.jp/hamusoku/imgs/b/5/b50e0b2b-s.jpg",
            "publishedAt": "2025-07-28T03:44:46Z",
            "content": "0 2025728 09:35 IDhamusoku\r\nYahoo pic.twitter.com/fgIUStBE2J\r\n— (@bc_qv_) July 27, 2025\r\n10 pic.twitter.com/d2iZceNG14\r\n— (@KFKBT_kate28) July 27, 2025\r\n— kz559999 (@VD7ciZ7kVDv9O2a) July 27, 2025\r\n—… [+426 chars]"
        },
        {
            "source": {
                "id": null,
                "name": "Boredpanda.com"
            },
            "author": "Justinas Keturka",
            "title": "76 Of The Wildest NYC Conversations People Can’t Believe They Heard (New Posts)",
            "description": "\"Most cities are nouns. New York is a verb.\" This quote is often attributed to John F. Kennedy, but even if he didn't say it, it still rings true today. New York is one of the world's most diverse cities with a population with over eight million people and ea…",
            "url": "https://www.boredpanda.com/funny-overheard-new-york-conversations/",
            "urlToImage": "https://www.boredpanda.com/blog/wp-content/uploads/2025/07/funny-overheard-new-york-conversations-fb.png",
            "publishedAt": "2025-07-28T07:10:09Z",
            "content": "\"Most cities are nouns. New York is a verb.\" This quote is often attributed to John F. Kennedy, but even if he didn't say it, it still rings true today. New York is one of the world's most diverse ci… [+470 chars]"
        },
        {
            "source": {
                "id": null,
                "name": "Deadline"
            },
            "author": "Max Goldbart",
            "title": "‘Criminal Record’ Producer STV Studios Hit By “Significant Commissioning Market Deterioration”",
            "description": "Criminal Record producer STV Studios has been hit by “significant commissioning market deterioration” over the past few months and has revised down its financials. Pointing to the “UK macroeconomic backdrop [having] worsened,” STV Studios owner STV said recen…",
            "url": "http://deadline.com/2025/07/stv-studios-hit-by-commissioning-downturn-1236471943/",
            "urlToImage": "https://deadline.com/wp-content/uploads/2024/08/CRIMINAL-RECORD.jpg?w=1024",
            "publishedAt": "2025-07-28T08:32:22Z",
            "content": "Criminal Record producer STV Studios has been hit by “significant commissioning market deterioration” over the past few months and has revised down its financials. \r\nPointing to the “UK macroeconomic… [+2575 chars]"
        },
        {
            "source": {
                "id": null,
                "name": "Andro4all.com"
            },
            "author": "JuanMi Guirado",
            "title": "Paga 250 euros menos por este MacBook Pro con 24 GB deRAM y 512 GB de almacenamiento",
            "description": "Antes, comprar un ordenador de Apple estaba destinado únicamente a la élite. Hoy en día, cualquiera puede hacerse con un Mac mini por unos 600 euros o un MacBook Air por 1000 euros. Sin embargo, hoy quiero recomendarte algo más especial, más Pro, se trata del…",
            "url": "https://andro4all.com/ofertas/paga-250-euros-menos-por-este-macbook-pro-con-24-gb-deram-y-512-gb-de-almacenamiento",
            "urlToImage": "https://andro4all.com/hero/2024/12/apple-macbook-pro-m4-trabajo.jpg?width=1200",
            "publishedAt": "2025-07-28T06:30:28Z",
            "content": "Diseño premium y durabilidad extrema para uno de los elegidos para formar parte de mi setup en el futuro\r\nAntes, comprar un ordenador de Apple estaba destinado únicamente a la élite. Hoy en día, cual… [+4001 chars]"
        },
        {
            "source": {
                "id": null,
                "name": "Impress.co.jp"
            },
            "author": "小板橋 望実",
            "title": "Amazonで「Apple Pencil（第2世代）」がセール",
            "description": "Amazon.co.jpで現在、Appleの「Apple Pencil（第2世代）」が割引価格で購入できる。",
            "url": "https://k-tai.watch.impress.co.jp/docs/news/sale/2034568.html",
            "urlToImage": "https://k-tai.watch.impress.co.jp/img/ktw/list/2034/568/1.jpg",
            "publishedAt": "2025-07-28T04:18:25Z",
            "content": "Amazon.co.jpAppleApple Pencil2 \r\n 218002017436 \r\n Apple Pencil2iPad Pro3456"
        },
        {
            "source": {
                "id": null,
                "name": "Impress.co.jp"
            },
            "author": "小板橋 望実",
            "title": "Amazonで「13インチiPad Air（M2）」が最大16％オフのセール",
            "description": "Amazon.co.jpで、Apple「13インチiPad Air（M2）」の128GBと256GBのWi-Fiモデルが最大16％オフで提供されている。",
            "url": "https://k-tai.watch.impress.co.jp/docs/news/sale/2034587.html",
            "urlToImage": "https://k-tai.watch.impress.co.jp/img/ktw/list/2034/587/1.jpg",
            "publishedAt": "2025-07-28T05:33:43Z",
            "content": "Amazon.co.jpApple13iPad AirM2128GB256GBWi-Fi16 \r\n 13iPad AirM2128GB Wi-Fi 1288001610782013iPad AirM2256GB Wi-Fi 1242429112800 \r\n 13iPad AirM211132AppleTouch IDWi-Fi 6E"
        },
        {
            "source": {
                "id": null,
                "name": "Impress.co.jp"
            },
            "author": "竹野 弘祐",
            "title": "iOS 26のパブリックベータ版が登場",
            "description": "アップル（Apple）は、今秋に正式リリースされるiPhoneのOS「iOS 26」のパブリックベータ版を公開した。あわせて、iPad向けの「iPadOS 26」、「macOS 26」などが公開されている。",
            "url": "https://k-tai.watch.impress.co.jp/docs/news/2034513.html",
            "urlToImage": "https://k-tai.watch.impress.co.jp/img/ktw/list/2034/513/cont0.jpg",
            "publishedAt": "2025-07-28T03:00:55Z",
            "content": "AppleiPhoneOSiOS 26iPadiPadOS 26macOS 26 \r\n iOS 26Liquid GlassSafariUI \r\n AIApple IntelligenceVisual Intelligence \r\n Apple Beta Software Program"
        },
        {
            "source": {
                "id": null,
                "name": "Nextpit.de"
            },
            "author": "Dustin Porth",
            "title": "Apple & Samsung zu teuer? Dieses Android-Tablet kostet keine 300 Euro!",
            "description": "Bei Amazon könnt Ihr Euch das Lenovo Idea Tab Pro aktuell für nicht einmal 300 Euro schnappen. Dabei macht das Android-Tablet (fast) alles richtig.",
            "url": "https://www.nextpit.de/deals/apple-samsung-zu-teuer-dieses-android-tablet-kostet-keine-300-euro",
            "urlToImage": "https://fs.npstatic.com/userfiles/7730515/image/Lenovo_Idea_Tab_Pro_circle_to_search-w1400h788.jpg",
            "publishedAt": "2025-07-28T08:53:11Z",
            "content": "Mit einem Tablet könnt Ihr nicht nur Abends auf der Couch die aktuellsten Tech-News verfolgen, sondern das Gerät auch als Smart-Home-Schaltzentrale oder treuen Reisebegleiter einsetzen. Auch das Leno… [+3251 chars]"
        },
        {
            "source": {
                "id": null,
                "name": "Tomshw.it"
            },
            "author": "Luca Zaninello",
            "title": "Samsung potrebbe eliminare lo sblocco dei bootloader",
            "description": "La community degli sviluppatori Android sta lanciando l'allarme su una decisione che potrebbe rivoluzionare l'approccio di Samsung alla personalizzazione dei propri dispositivi. Con l'arrivo di One UI...",
            "url": "https://www.tomshw.it/smartphone/samsung-potrebbe-bloccare-lunlock-del-bootloader-2025-07-28",
            "urlToImage": "https://www.tomshw.it/storage/media/2025/05/56966/samsung-galaxy-s25-edge-26.jpg",
            "publishedAt": "2025-07-28T07:50:29Z",
            "content": "La community degli sviluppatori Android sta lanciando l'allarme su una decisione che potrebbe rivoluzionare l'approccio di Samsung alla personalizzazione dei propri dispositivi. Con l'arrivo di One U… [+4254 chars]"
        },
        {
            "source": {
                "id": null,
                "name": "Techbang.com"
            },
            "author": "WL.",
            "title": "如何開啟 iPhone 內建的免費環境音樂？",
            "description": "在 iOS 18.4 的更新中，加入全新的「環境音樂」功能，讓使用者可透過控制中心播放適合不同情境的背景音樂，以幫助睡眠、舒緩壓力及提升生活品質。近期 Apple 在 iOS 18.4 的更新中，加入全新的「環境音樂」功能，讓使用者可透過控制中心播放適合不同情境的背景音樂，以幫助睡眠、舒緩壓力及提升生活品質。另外，環境音樂有睡眠、放鬆、生產力和身心健康四大主題，精選 Apple Music 播放清單，提供符合情境的音樂或聲音，甚至還能自訂喜愛的歌單來播放。\n步驟 1：進入 iPhone 控制中心頁面，按下左上角的…",
            "url": "https://www.techbang.com/posts/122849-add-ambient-music-to-iphone-control-center",
            "urlToImage": "https://cdn1.techbang.com/system/excerpt_images/122849/original/bf7def7b499ad615ea53485dca438b77.jpg?1745831406",
            "publishedAt": "2025-07-28T05:30:00Z",
            "content": "Apple iOS 18.4 Apple Music \r\n 1 iPhone + \r\n2+ \r\n3\r\n4\r\n5\r\n6 Apple Music \r\nPC home \r\nPC home"
        },
        {
            "source": {
                "id": null,
                "name": "Forbes"
            },
            "author": "David Phelan, Senior Contributor, \n David Phelan, Senior Contributor\n https://www.forbes.com/sites/appleunboxed/",
            "title": "Apple’s Surprise Free Offer To iPhone 13 Users Is Now Live For iPhones",
            "description": "If you have an iPhone 13 or later, the “game-changer” new upgrade from T-Mobile and Starlink is now live — even if T-Mobile isn’t your carrier.",
            "url": "https://www.forbes.com/sites/davidphelan/2025/07/28/apples-surprise-free-offer-to-iphone-13-users-is-now-live-for-iphones-and-more-t-satellite/",
            "urlToImage": "https://imageio.forbes.com/specials-images/imageserve/6827a34ca2f3326327c41a95/0x0.jpg?format=jpg&height=900&width=1600&fit=bounds",
            "publishedAt": "2025-07-28T07:53:19Z",
            "content": "Updated July 27 with more details of T-Satellite including early reviews of the service now its gone live.\r\nWhen Apple made the surprise announcement that its iPhone 13 series was suddenly compatible… [+5339 chars]"
        },
        {
            "source": {
                "id": null,
                "name": "Forbes"
            },
            "author": "Zinnia Lee, Forbes Staff, \n Zinnia Lee, Forbes Staff\n https://www.forbes.com/sites/zinnialee/",
            "title": "Samsung Foundry Signs $16.5 Billion Deal With Tesla To Make AI Chips",
            "description": "Tesla chief Elon Musk said on Monday his company is working with the South Korean giant to produce the next-generation AI6 chip at Samsung’s Texas fab.",
            "url": "https://www.forbes.com/sites/zinnialee/2025/07/28/samsung-foundry-signs-165-billion-deal-with-tesla-to-make-ai-chips/",
            "urlToImage": "https://imageio.forbes.com/specials-images/imageserve/6887254d8e5e1a384d385881/0x0.jpg?format=jpg&crop=2695,1515,x0,y139,safe&height=900&width=1600&fit=bounds",
            "publishedAt": "2025-07-28T08:20:37Z",
            "content": "The Tesla deal gives a much-needed boost to Samsungs loss-making contract chipmaking business.\r\nJoan Cros/NurPhoto via Getty Images\r\nSamsung Electronics, controlled by South Korean billionaire Jay Y.… [+2407 chars]"
        },
        {
            "source": {
                "id": null,
                "name": "Forbes"
            },
            "author": "Michael Harley, Contributor, \n Michael Harley, Contributor\n https://www.forbes.com/sites/michaelharley/",
            "title": "Reinventing An Icon: The 2026 Honda Prelude Vs. Its 2001 Predecessor",
            "description": "After a 25-year absence, Honda has announced the return of the Prelude. With advanced technology and a hybrid powertrain, it will be unrecognizable from its predecessor.",
            "url": "https://www.forbes.com/sites/michaelharley/2025/07/28/reinventing-an-icon-the-2026-honda-prelude-vs-its-2001-predecessor/",
            "urlToImage": "https://imageio.forbes.com/specials-images/imageserve/68870b5618598e6402164366/0x0.jpg?format=jpg&height=900&width=1600&fit=bounds",
            "publishedAt": "2025-07-28T05:39:06Z",
            "content": "LOS ANGELES, CALIFORNIA - NOVEMBER 24: The Honda Prelude Concept is on display during the 2023 Los ... More Angeles Auto Show at the Los Angeles Convention Center on November 24, 2023 in Los Angeles,… [+4416 chars]"
        },
        {
            "source": {
                "id": null,
                "name": "ComputerBase"
            },
            "author": "Nicolas La Rocco",
            "title": "Apple-Gerüchte: iPhone 17 Pro mit 8x-Zoom und Pro-Kamera-App erwartet",
            "description": "In sechs Wochen dürfte die Vorstellung der iPhone-17-Familie erfolgen, darunter auch das iPhone 17 Pro und iPhone 17 Pro Max. Für Apples Pro-Modelle soll es ein Teleobjektiv mit stärkerer Vergrößerung, eine neue Pro-Kamera-App und erweiterte Bedienelemente im…",
            "url": "https://www.computerbase.de/news/smartphones/apple-geruechte-iphone-17-pro-mit-8x-zoom-und-pro-kamera-app-erwartet.93677/",
            "urlToImage": "https://pics.computerbase.de/1/1/8/6/0/6-ce03ef47677f5e49/article-1280x720.68b6f003.jpg",
            "publishedAt": "2025-07-28T09:11:00Z",
            "content": "In sechs Wochen dürfte die Vorstellung der iPhone-17-Familie erfolgen, darunter auch das iPhone 17 Pro und iPhone 17 Pro Max. Für Apples Pro-Modelle soll es ein Teleobjektiv mit stärkerer Vergrößerun… [+2814 chars]"
        },
        {
            "source": {
                "id": null,
                "name": "ComputerBase"
            },
            "author": "Volker Rißka",
            "title": "Chip-Fertigung in SF2A: Samsung Foundry gewinnt Milliarden­auftrag von Tesla",
            "description": "Es ist der Erfolg, den Samsung brauchte: Tesla wechselt von TSMC zusätzlich auch wieder zurück zu Samsung und wird dort Chips für viele Milliarden US-Dollar fertigen lassen. Es ist auch der größte Erfolg, den Samsungs Erweiterung der Foundry-Sparte in den USA…",
            "url": "https://www.computerbase.de/news/wirtschaft/chip-fertigung-in-sf2a-samsung-foundry-gewinnt-milliardenauftrag-von-tesla.93675/",
            "urlToImage": "https://pics.computerbase.de/1/1/8/6/0/4-c335ddf8469f69ee/article-1280x720.fcb4436c.jpg",
            "publishedAt": "2025-07-28T06:54:00Z",
            "content": "Es ist der Erfolg, den Samsung brauchte: Tesla wechselt von TSMC zusätzlich auch wieder zurück zu Samsung und wird dort Chips für viele Milliarden US-Dollar fertigen lassen. Es ist auch der größte Er… [+2107 chars]"
        },
        {
            "source": {
                "id": null,
                "name": "Antyweb.pl"
            },
            "author": "Kamil Świtalski",
            "title": "iPhone 17 Pro będzie łakomym kąskiem dla wszystkich fanów fotografii. Obok tych zmian nie przejdą obojętnie",
            "description": "Tegoroczne iPhone'y z serii Pro miałyby wprowadzić zmiany w zoomie oferowanym w aplikacji. Tym razem miałoby to być nawet 8x, a na tym jeszcze nie koniec nowości.",
            "url": "https://antyweb.pl/iphone-17-pro-bedzie-lakomym-kaskiem-dla-wszystkich-fanow-fotografii-obok-tych-zmian-nie-przejda-obojetnie",
            "urlToImage": "https://static.antyweb.pl/img/w_1250,h_550/wp-content/uploads/2025/07/iphone-15-pro-24.jpg",
            "publishedAt": "2025-07-28T06:00:59Z",
            "content": "wiat technologii nieustannie yje spekulacjami na temat nadchodzcej serii iPhone'ów. To truizm, ale niestety tak ju jest: po premierze najnowszych iPhone'ów, ju zaczyna si fala spekulacji na temat kol… [+2894 chars]"
        },
        {
            "source": {
                "id": null,
                "name": "Iphoneitalia.com"
            },
            "author": "Francesco Siciliani",
            "title": "iPhone 17 Pro: nuovo rumor parla di tre novità per la fotocamera",
            "description": "Una fonte anonima parla di tre ipotetiche novità di iPhone 17 Pro in merito al comparto fotografico. \nLink all'articolo originale: iPhone 17 Pro: nuovo rumor parla di tre novità per la fotocamera",
            "url": "https://www.iphoneitalia.com/840380/iphone-17-pro-nuovo-rumor-parla-di-tre-novita-per-la-fotocamera",
            "urlToImage": "https://static.iphoneitalia.com/wp-content/uploads/2025/07/iPhone-17-Pro-on-Desk-Centered-1.jpg",
            "publishedAt": "2025-07-28T09:02:38Z",
            "content": "In attesa della presentazione di iPhone 17 Pro, prevista per il mese di settembre, un nuovo rumor parla delle possibili novità della fotocamera.\r\nStando a quanto affermato da MacRumors, che ha ricevu… [+1516 chars]"
        },
        {
            "source": {
                "id": null,
                "name": "iLounge"
            },
            "author": "Samantha Wiley",
            "title": "Apple Outs New Customizable Wallpaper Tool",
            "description": "Apple recently introduced a new wallpaper tool along with its online Apple Store launch in Saudi Arabia. There’s a new page where users can create their own wallpapers. The central theme of it is the Apple logo, which is available in five different designs. U…",
            "url": "https://www.ilounge.com/news/apple/apple-outs-new-customizable-wallpaper-tool",
            "urlToImage": "https://www.ilounge.com/wp-content/uploads/2025/07/apple-wallpaper_desktop-1-scaled-1.webp",
            "publishedAt": "2025-07-28T06:46:50Z",
            "content": "Apple recently introduced a new wallpaper tool along with its online Apple Store launch in Saudi Arabia.\r\nThere’s a new page where users can create their own wallpapers. The central theme of it is th… [+688 chars]"
        },
        {
            "source": {
                "id": null,
                "name": "iLounge"
            },
            "author": "Samantha Wiley",
            "title": "Apple is Changing Age Ratings on App Store",
            "description": "Apple has announced new changes coming to the App Store Age Ratings. Three new tiers have been added to the age ratings, namely 18+, 16+, and 13+ to the existing ratings of 9+ and 4+. In addition, the 17+ and 12+ ratings will be removed. The changes are for p…",
            "url": "https://www.ilounge.com/news/apple/apple-is-changing-age-ratings-on-app-store",
            "urlToImage": "https://www.ilounge.com/wp-content/uploads/2025/07/01rFWdAcFn0IolHF0PXVoyb-1.webp",
            "publishedAt": "2025-07-28T06:49:22Z",
            "content": "Apple has announced new changes coming to the App Store Age Ratings.\r\nThree new tiers have been added to the age ratings, namely 18+, 16+, and 13+ to the existing ratings of 9+ and 4+. In addition, t… [+724 chars]"
        },
        {
            "source": {
                "id": null,
                "name": "iLounge"
            },
            "author": "Samantha Wiley",
            "title": "The 2025 iPad Wi-Fi 128GB is $50 Off",
            "description": "The base model iPad is a workhorse in the entertainment and general tasks department. Today, the Wi-Fi 128GB variant is down to just $299 from its original price of $350 on Amazon. This year’s base iPad offers a lot of unique color options, perfect for kids a…",
            "url": "https://www.ilounge.com/news/daily-deals/the-2025-ipad-wi-fi-128gb-is-50-off",
            "urlToImage": "https://www.ilounge.com/wp-content/uploads/2025/07/Apple-iPad-Mini-2024-featured-image.jpg.webp",
            "publishedAt": "2025-07-28T06:50:48Z",
            "content": "The base model iPad is a workhorse in the entertainment and general tasks department. Today, the Wi-Fi 128GB variant is down to just $299 from its original price of $350 on Amazon.\r\nThis year’s base … [+689 chars]"
        },
        {
            "source": {
                "id": null,
                "name": "iLounge"
            },
            "author": "Samantha Wiley",
            "title": "AirPods 4 and AirPods Pro 2 Get New Public Beta Firmware",
            "description": "Public beta testers can now download and install a new beta firmware for the AirPods 4 and AirPods Pro 2. The beta firmware contains features for the AirPods within macOS Tahoe, iPadOS 26, and iOS 26. It’s worth noting that the update is only for public beta …",
            "url": "https://www.ilounge.com/news/airpods-pro/airpods-4-and-airpods-pro-2-get-new-public-beta-firmware",
            "urlToImage": "https://www.ilounge.com/wp-content/uploads/2025/07/64329-134042-50478-99481-AirPods-Pro-2-with-case-xl-xl.jpg",
            "publishedAt": "2025-07-28T06:48:18Z",
            "content": "Public beta testers can now download and install a new beta firmware for the AirPods 4 and AirPods Pro 2.\r\nThe beta firmware contains features for the AirPods within macOS Tahoe, iPadOS 26, and iOS 2… [+666 chars]"
        },
        {
            "source": {
                "id": null,
                "name": "Olhardigital.com.br"
            },
            "author": "Ana Bondance",
            "title": "5 eletrônicos da Apple já enviados ao espaço",
            "description": "Veja 5 dispositivos eletrônicos da Apple que já foram enviados ao espaço e seu impacto direto na exploração espacial.\nO post 5 eletrônicos da Apple já enviados ao espaço apareceu primeiro em Olhar Digital.",
            "url": "https://olhardigital.com.br/2025/07/28/reviews/5-eletronicos-da-apple-ja-enviados-ao-espaco/",
            "urlToImage": "https://img.odcdn.com.br/wp-content/uploads/2025/06/Apple-no-espao-via-Nasa-Unsplash-Olhar-Digital.png",
            "publishedAt": "2025-07-28T05:00:00Z",
            "content": "Os produtos da Apple deixaram sua marca em muitos setores, do entretenimento aos negócios, mas sua presença no espaço pode surpreender algumas pessoas. Embora muita gente suponha que a NASA e demais … [+5171 chars]"
        },
        {
            "source": {
                "id": null,
                "name": "Olhardigital.com.br"
            },
            "author": "Ana Bondance",
            "title": "6 celulares antigos que já foram moda na sua infância ou adolescência",
            "description": "A evolução dos telefones celulares aconteceu muito rápido nos anos 2000; veja modelos antigos que foram moda na época.\nO post 6 celulares antigos que já foram moda na sua infância ou adolescência apareceu primeiro em Olhar Digital.",
            "url": "https://olhardigital.com.br/2025/07/28/reviews/6-celulares-antigos-que-ja-foram-moda-na-sua-infancia-ou-adolescencia/",
            "urlToImage": "https://img.odcdn.com.br/wp-content/uploads/2025/06/Celulares-anos-2000-Olhar-Digital.png",
            "publishedAt": "2025-07-28T04:00:00Z",
            "content": "Os primeiros celulares foram lançados nos anos 1980, mas eles eram grandes, pesados e pouco práticos. Esses aparelhos eram usados quase exclusivamente para chamadas e mensagens. Com o tempo, no entan… [+5036 chars]"
        },
        {
            "source": {
                "id": null,
                "name": "3dnews.ru"
            },
            "author": null,
            "title": "Japan Display фактически прекратит выпуск OLED-панелей для умных часов, обездолив Apple",
            "description": "Трудности японских производителей ЖК-дисплеев в борьбе с южнокорейскими и китайскими конкурентами наблюдаются уже не первый год подряд, и на новом витке деградации японской промышленности компания Japan Display приняла решение продать всё оборудование для вып…",
            "url": "https://3dnews.ru/1126653/japan-display-fakticheski-prekratit-vipusk-oledpaneley-dlya-umnih-chasov-obezdoliv-apple",
            "urlToImage": "https://3dnews.ru/assets/external/illustrations/2025/07/28/1126653/jdi_01.jpg",
            "publishedAt": "2025-07-28T05:44:00Z",
            "content": "- , Japan Display OLED, Apple Watch.\r\n: Japan Display\r\nJapan Display - OLED- . , , Japan Display . Japan Display OLED , , . Apple, OLED- Watch.\r\n , Japan Display , - . . - HKC, . Japan Display . 2023… [+147 chars]"
        },
        {
            "source": {
                "id": null,
                "name": "Geekpark.net"
            },
            "author": null,
            "title": "特斯拉廉价 Model Y 减配内饰曝光；Firefox 终止中国账户运营；宇树王兴兴：经常偷懒，用 AI 写代码｜极客早知道",
            "description": "消息称特斯拉第三代机器人即将进入中国 C 端市场，预计明年实现量产\n7 月 27 日消息，特斯拉相关人士向《科创板日报》记者透露，目前特斯拉第三代机器人已在美国工厂进行实测，预计 2025 年面向中国 C 端市场推出，将进入家庭等消费场景，预计 2026 年实现量产，计划 5 年内年产 100 万台。\n\n据了解，特斯拉 Optimus 人形机器人项目自 2021 年首次亮相以来已取得显著进展，目前已完成两代产品迭代。\n第二代 Optimus 相比初代实现了多项突破：重量减轻约 10 公斤，行走速度提升 30%，手…",
            "url": "https://www.geekpark.net/news/351963",
            "urlToImage": "https://imgslim.geekpark.net/uploads/image/file/8a/68/8a68015189393f005519f2804061c633.png",
            "publishedAt": "2025-07-28T00:17:56Z",
            "content": "C \r\n7 27 2025 C 2026 5 100 \r\nOptimus 2021 \r\n Optimus 10 30% 22 28 \r\n 2025 Optimus \r\n 2025 Optimus V3 V3 Optimus V3 \r\n 2025 1-1.2 2026 10 2027 50 \r\n 2030 2035 1.12 IT \r\nAI \r\n7 27 2025 AI \r\nIT AI \r\n AI… [+1121 chars]"
        },
        {
            "source": {
                "id": null,
                "name": "Everything-everywhere.com"
            },
            "author": "Gary Arndt",
            "title": "Zoroastrianism",
            "description": "Podcast Transcript Sometime between the 7th and 13th century BC, a man was born in Eastern Persia who had a revolutionary idea.  He claimed that there weren’t multiple gods, but rather just one god.  He established a religion which, at various times, was one …",
            "url": "https://everything-everywhere.com/zoroastrianism/",
            "urlToImage": "https://photos.smugmug.com/Other/n-hRFP2/Podcast-Images/i-MCrnJ6X/0/MgX844NSLMBStSN9sGNDjccdhZvhgPFdgRCrbKSnM/L/1848epart-L.jpg",
            "publishedAt": "2025-07-28T06:28:15Z",
            "content": "Subscribe Apple | Spotify | Amazon |iHeart Radio | Castbox | Podcast Republic | RSS | Patreon | Discord | Facebook\r\nSometime between the 7th and 13th century BC, a man was born in Eastern Persia who … [+12817 chars]"
        },
        {
            "source": {
                "id": null,
                "name": "Tinhte.vn"
            },
            "author": "no-reply@tinhte.vn (Pnghuy), Pnghuy",
            "title": "F1: The Movie của Apple cán mốc doanh thu 500 triệu USD",
            "description": "F1: The Movie của Apple cán mốc doanh thu 500 triệu USD\n \nTính đến tuần cuối cùng của tháng 7, bộ phim F1: The Movie của Apple đã đạt mốc doanh thu 500 triệu USD, ngang bằng với Superman bản remake của Warner Bros, tính trên phạm vi toàn cầu.",
            "url": "https://tinhte.vn/thread/f1-the-movie-cua-apple-can-moc-doanh-thu-500-trieu-usd.4041397/",
            "urlToImage": "https://photo2.tinhte.vn/data/attachment-files/2025/07/8793876_cover-f1-500-trieu-USD.webp",
            "publishedAt": "2025-07-28T00:30:41Z",
            "content": "F1: The Movie ca Apple cán mc doanh thu 500 triu USDTính n tun cui cùng ca tháng 7, b phim F1: The Movie ca Apple ã t mc doanh thu 500 triu USD, ngang bng vi Superman bn remake ca Warner Bros, tính t… [+746 chars]"
        },
        {
            "source": {
                "id": null,
                "name": "Theregister.com"
            },
            "author": "Iain Thomson",
            "title": "US spy satellite agency breached, but insists no classified secrets spilled",
            "description": "Plus, leak site for BlackSuit seized, Tea spilt, and avoid crime if you've got a famous dad Infosec in brief  A computer intrusion hit the US spy satellite agency, but officials insist no classified secrets were lost - just some unclassified ones, apparently.…",
            "url": "https://www.theregister.com/2025/07/28/infosec_in_brief/",
            "urlToImage": "https://regmedia.co.uk/2018/03/06/spy_vs_spy_shutterstock_editorial_only_phillip_maguire.jpg",
            "publishedAt": "2025-07-28T00:29:06Z",
            "content": "Infosec in brief A computer intrusion hit the US spy satellite agency, but officials insist no classified secrets were lost - just some unclassified ones, apparently.\r\nThe National Reconnaissance Off… [+7744 chars]"
        },
        {
            "source": {
                "id": null,
                "name": "Macitynet.it"
            },
            "author": "Fabrizio Frattini",
            "title": "Rumor iPhone 17 Pro, tre cose che potrebbero rivoluzionare come fotografiamo",
            "description": "Un rumor anonimo anticipa tre novità sorprendenti per l’iPhone 17 Pro che potrebbero rivoluzionare l'esperienza fotografica. Ma la mancanza totale di riscontri e elementi che sarebbero più che sorprendenti, il racconto affonda sotto la linea di galleggiamento…",
            "url": "https://www.macitynet.it/?p=1421875",
            "urlToImage": "https://www.macitynet.it/wp-content/uploads/2019/06/logomacitynet1200wide-1.jpg",
            "publishedAt": "2025-07-28T05:48:20Z",
            "content": "Un iPhone che diventa una specie di compatta superzoom. Il profilo lo disegna un nuovo e rumor da prendere con le dovute cautele apparso ieri sulle pagine di MacRumors.\r\nLo voce, che appare a poche s… [+4106 chars]"
        },
        {
            "source": {
                "id": null,
                "name": "Hwupgrade.it"
            },
            "author": null,
            "title": "NVIDIA N1X: SoC ARM con GPU Blackwell da 6144 core supera tutte le iGPU moderne",
            "description": "Il SoC NVIDIA N1X, basato su architettura ARM e GPU Blackwell, emerge su Geekbench con 6144 core CUDA e un punteggio che supera le attuali iGPU concorrenti. Purtroppo, come da indiscrezioni recenti, il SoC per notebook e non solo si farà verosimilmente attend…",
            "url": "https://www.hwupgrade.it/news/cpu/nvidia-n1x-soc-arm-con-gpu-blackwell-da-6144-core-supera-tutte-le-igpu-moderne_141642.html",
            "urlToImage": "https://www.hwupgrade.it/i/n/geforce-rtx-4000-laptop_720.jpg",
            "publishedAt": "2025-07-28T08:01:01Z",
            "content": "Dopo le indiscrezioni sul rinvio al 2026 per svariati problemi sia di carattere hardware che software, il SoC N1X di NVIDIA torna a far parlare di sé. Un recente test apparso su Geekbench, relativi a… [+1906 chars]"
        },
        {
            "source": {
                "id": null,
                "name": "Hwupgrade.it"
            },
            "author": null,
            "title": "Pebble è di nuovo Pebble. Ecco il ritorno ufficiale di un nome storico degli smartwatch",
            "description": "Pebble, lo storico brand di smartwatch, fa il suo sorprendente ritorno grazie al recupero del marchio da parte del fondatore Eric Magicovsky. Una mossa che va oltre il semplice nome e promette di rivoluzionare il segmento degli indossabili con una rinnovata a…",
            "url": "https://www.hwupgrade.it/news/wearables/pebble-e-di-nuovo-pebble-ecco-il-ritorno-ufficiale-di-un-nome-storico-degli-smartwatch_141653.html",
            "urlToImage": "https://www.hwupgrade.it/i/n/Pebblenewwatch_720.jpg",
            "publishedAt": "2025-07-28T07:31:01Z",
            "content": "Chiunque abbia un minimo di passione per il mondo dell’hardware indossabile conosce il nome Pebble. Un nome che, molti anni prima che Apple e Samsung proponessero i loro orologi hi-tech, rappresentav… [+4141 chars]"
        },
        {
            "source": {
                "id": null,
                "name": "Shutterbean.com"
            },
            "author": null,
            "title": "Intentions for the Week",
            "description": "Intentions for the Week- Week 31 in 2025\nHi hiiiiii! Here we are. Week 31. Bing! \nDid you have any time to yourself? (I sure did!!)\nDid you get some outdoor time? (I DID!) \nAre you going to move your body today? Here’s some inspiration to start a workout rout…",
            "url": "https://www.shutterbean.com/2025/intentions-for-the-week-421/",
            "urlToImage": "https://www.shutterbean.com/wp-content/uploads/2021/11/intentionsfortheweekworkbook-10.jpg",
            "publishedAt": "2025-07-28T09:22:09Z",
            "content": "Intentions for the Week- Week 31 in 2025\r\nHi hiiiiii! Here we are. Week 31. Bing! \r\nDid you have any time to yourself?  (I sure did!!)\r\nDid you get some outdoor time? (I DID!) \r\nAre you going to move… [+3637 chars]"
        },
        {
            "source": {
                "id": null,
                "name": "Sspai.com"
            },
            "author": "少数派编辑部",
            "title": "具透 | macOS Tahoe 26 推出公开测试版，你能提前看到这些亮点",
            "description": "macOS Tahoe 26 为我们带来了新的视觉风格，改进了聚焦搜索、控制中心、菜单栏等内置应用。查看全文",
            "url": "https://sspai.com/post/101018",
            "urlToImage": "https://cdnfile.sspai.com/7/28/2025/article/58d7ea68-df22-b617-190e-f04f36e33994.png",
            "publishedAt": "2025-07-28T07:00:00Z",
            "content": "7 25 Apple Mac macOS Tahoe 26 Public Beta Apple bug macOS Tahoe 26 \r\n macOS Tahoe 26 \r\niOS / iPadOS 26 Public Beta &amp; \r\n bug \r\nApple macOS Tahoe 26 Mac OS X 10.10 UI visionOS Liquid Glass\r\nLiquid … [+1047 chars]"
        },
        {
            "source": {
                "id": null,
                "name": "Sapo.pt"
            },
            "author": "Pedro Simões",
            "title": "Utilizadores Android são melhores a evitar burlas do que os do iPhone",
            "description": "Uma nova investigação revela uma conclusão surpreendente sobre a segurança no universo dos smartphones. Os utilizadores de iPhone são mais propensos a serem vítimas de burlas e demonstram menor consciência sobre segurança móvel em...",
            "url": "https://pplware.sapo.pt/smartphones-tablets/android/utilizadores-android-sao-melhores-a-evitar-burlas-do-que-os-do-iphone/",
            "urlToImage": "https://pplware.sapo.pt/wp-content/uploads/2025/07/iphone_vs_android_seguranca_1.jpg",
            "publishedAt": "2025-07-28T08:00:52Z",
            "content": "Uma nova investigação revela uma conclusão surpreendente sobre a segurança no universo dos smartphones. Os utilizadores de iPhone são mais propensos a serem vítimas de burlas e demonstram menor consc… [+2916 chars]"
        },
        {
            "source": {
                "id": null,
                "name": "Macotakara.jp"
            },
            "author": "danbo",
            "title": "PayPay、App StoreなどAppleサービスの支払で最大10％ポイント付与キャンペーン実施中（8/3まで）",
            "description": "PayPay最大10％ポイント付与クーポンキャンペーン\r\n\n\n\n\n\n\n\n\n\n\n\n\n\n\n\n\n\n\n\n\n\n\n\n\n\n\n\n\n\n\n\n\n\n\n\n\n\n\n\n\n\n\n\n\n\n\n\n\n\n<!-- テキスト -->\n\nPayPayが、App StoreやApple Accountのチャージで「PayPay最大10％ポイント付与クーポンキャンペーン」を実施しています。\n\nキャンペーン期間は、2025年7月28日〜2025年8月3日までとなります。\n\n使える回数は5回で、1回の付与ポイント上限は50ポイントで、合計の付与ポイント上限は250ポイント…",
            "url": "https://www.macotakara.jp/news/entry-49268.html",
            "urlToImage": "https://www.macotakara.jp/archives/001/202507/1b23183f0b52d96a.jpg",
            "publishedAt": "2025-07-28T06:47:08Z",
            "content": "PayPayApp StoreApple AccountPayPay10\r\n2025728202583\r\n5150250"
        },
        {
            "source": {
                "id": null,
                "name": "MacGeneration"
            },
            "author": "Pierre Dandumont",
            "title": "Les puces M3 Pro et M3 Max n'ont pas exactement les mêmes cœurs",
            "description": "Apple est une société assez secrète pour ses processeurs, et ne donne que peu d'informations sur les différents systèmes sur puce qui animent nos Mac, iPhone et autres Apple Watch. Contrairement à Intel, AMD ou ARM qui donnent des détails sur les architecture…",
            "url": "https://www.macg.co/materiel/2025/07/les-puces-m3-pro-et-m3-max-nont-pas-exactement-les-memes-coeurs-302789",
            "urlToImage": "https://cdn.mgig.fr/2025/07/mga-a31cfc89-w375-w1500-w750_accroche.jpg",
            "publishedAt": "2025-07-28T08:41:33Z",
            "content": "Apple est une société assez secrète pour ses processeurs, et ne donne que peu d'informations sur les différents systèmes sur puce qui animent nos Mac, iPhone et autres Apple Watch. Contrairement à In… [+2232 chars]"
        },
        {
            "source": {
                "id": null,
                "name": "Iphones.ru"
            },
            "author": "Артём Баусов",
            "title": "iPhone 17 Pro получит 8-кратный оптический зум и новое приложение Камера с расширенными настройками",
            "description": "Источник MacRumors сообщил, что iPhone 17 Pro получат несколько улучшений, касаемых камеры. Инсайдер утверждает, что работает в компании, которая занимается производством рекламы. И по этой причине он владеет некоторой маркетинговой информацией. Надежность ис…",
            "url": "https://www.iphones.ru/iNotes/iphone-17-pro-poluchit-8-kratnyy-opticheskiy-zum-i-novoe-prilozhenie-kamera-s-rasshirennymi-nastroykami",
            "urlToImage": "https://www.iphones.ru/wp-content/plugins/wonderm00ns-simple-facebook-open-graph-tags/fbimg.php?img=https%3A%2F%2Fwww.iphones.ru%2Fwp-content%2Fuploads%2F2025%2F07%2FIMG_4508.jpeg",
            "publishedAt": "2025-07-28T05:15:40Z",
            "content": "MacRumors , iPhone 17 Pro , .\r\n , , . . .\r\n, :\r\n 8× 5× iPhone 16 Pro. -, , \r\n Apple, , . Halide, Kino Filmic Pro. , iPhone 17 Pro\r\n . iPhone 16\r\n , Apple . , Final Cut Camera. [MacRumors]"
        },
        {
            "source": {
                "id": null,
                "name": "Expansion.com"
            },
            "author": "Amaia Ormaetxea, Raquel Moreno",
            "title": "La Primera de Expansión sobre el pacto entre UE y EEUU, Sabadell, Santander, apagón nuclear, Milei y Gaza",
            "description": "Europa se pliega a Estados Unidos y Donald Trump: aranceles del 15% compras millonarias. La Unión Europea acepta el marco negociador de Trump y se compromete a \"reequilibrar\" el comercio transatlántico aceptando altos gravámenes y comprometiéndose a invertir …",
            "url": "https://www.expansion.com/podcasts/la-primera-de-expansion/2025/07/28/688706fde5fdea4e6f8b459a.html",
            "urlToImage": "https://phantom-expansion.uecdn.es/3103fab2439ecdfc7f75c19a376dbce7/f/webp/assets/multimedia/imagenes/2025/07/28/17536796066828.jpg",
            "publishedAt": "2025-07-28T05:29:25Z",
            "content": "Europa se pliega a Estados Unidos y Donald Trump: aranceles del 15% compras millonarias. La Unión Europea acepta el marco negociador de Trump y se compromete a \"reequilibrar\" el comercio transatlánti… [+941 chars]"
        },
        {
            "source": {
                "id": null,
                "name": "AdExchanger"
            },
            "author": "AdExchanger",
            "title": "Is The ‘G’ For Google?; The Canadian Revolution",
            "description": "ChatGPT will google that for you; the Canadian TikTok shutdown gets real; and Elon’s crusage against media ratings organizations goes on.\nThe post Is The ‘G’ For Google?; The Canadian Revolution appeared first on AdExchanger.",
            "url": "http://www.adexchanger.com/daily-news-roundup/monday-28072025/",
            "urlToImage": "https://www.adexchanger.com/wp-content/uploads/2025/01/tiktok-the-end-thumbnail.jpg",
            "publishedAt": "2025-07-28T04:03:55Z",
            "content": "Heres todays AdExchanger.com news round-up Want it by email? Sign up here.\r\nThe Old Ways Still Work\r\nRemember Let Me Google That For You? \r\nIt was a website people would passive-aggressively send to … [+4799 chars]"
        },
        {
            "source": {
                "id": null,
                "name": "Zive.cz"
            },
            "author": "Martin Chroust",
            "title": "Aktuální iPhony mají oproti tomu prvnímu 385× výkonnější procesor. iPhone 17 Pro by měl tento rozdíl ještě výrazně zvýšit",
            "description": "Apple má rád čísla a na prezentacích iPhonů se často chlubí mezigeneračními nárůsty výkonu v násobcích či procentech. Co by se však stalo, kdyby se porovnal výkon procesoru prvního iPhonu z roku 2007 se zatím stále aktuálním iPhonem 16 Pro ? Podle analýzy jap…",
            "url": "https://mobilmania.zive.cz/clanky/aktualni-iphony-maji-oproti-tomu-prvnimu-385-vykonnejsi-procesor-iphone-17-pro-by-mel-tento-rozdil-jeste-vyrazne-zvysit/sc-3-a-1363111/default.aspx",
            "urlToImage": "https://mobilmania.zive.cz/getthumbnail.aspx?q=100&height=20000&width=20000&id_file=921744229",
            "publishedAt": "2025-07-28T08:50:00Z",
            "content": "Apple má rád ísla a na prezentacích iPhon se asto chlubí mezigeneraními nársty výkonu v násobcích i procentech. Co by se vak stalo, kdyby se porovnal výkon procesoru prvního iPhonu z roku 2007 se zat… [+2298 chars]"
        },
        {
            "source": {
                "id": null,
                "name": "iphone-ticker.de › iPhone-News seit 2007"
            },
            "author": "Nicolas",
            "title": "Apple Health MCP Server: KI-Zugriff auf die eigenen Gesundheitsdaten",
            "description": "Ein neues Projekt ermöglicht den direkten Zugriff auf Apple Health Daten über einen MCP-Server. Die Abkürzung MCP steht für Model Context Protocol und beschreibt einen Standard, der die Verbindung von KI-Anwendungen mit verschiedenen Datenquellen erleichtert.…",
            "url": "https://www.iphone-ticker.de/apple-health-mcp-server-ki-zugriff-auf-eure-gesundheitsdaten-260865/",
            "urlToImage": "https://images.iphone-ticker.de/wp-content/uploads/2023/12/apple-watch-feature.jpg",
            "publishedAt": "2025-07-28T05:28:39Z",
            "content": "Ein neues Projekt ermöglicht den direkten Zugriff auf Apple Health Daten über einen MCP-Server. Die Abkürzung MCP steht für Model Context Protocol und beschreibt einen Standard, der die Verbindung vo… [+1919 chars]"
        },
        {
            "source": {
                "id": null,
                "name": "iphone-ticker.de › iPhone-News seit 2007"
            },
            "author": "Nicolas",
            "title": "Kompaktlader mit integriertem Kabel: Anker stellt neues Netzteil vor",
            "description": "Der Zubehör-Anbieter Anker hat ein neues USB-C-Ladegerät vorgestellt, das auf Nutzer abzielt, die eine kompakte Ladelösung für unterwegs suchen, bei der das USB-C-Kabel bereits integriert ist. Das Anker Nano 35W ist mit zwei USB-C-Anschlüssen und einem integr…",
            "url": "https://www.iphone-ticker.de/kompaktlader-mit-integriertem-kabel-anker-stellt-neues-netzteil-vor-260885/",
            "urlToImage": "https://images.iphone-ticker.de/wp-content/uploads/2025/07/anker-kabel-netzteil-feature.jpg",
            "publishedAt": "2025-07-28T07:27:08Z",
            "content": "Der Zubehör-Anbieter Anker hat ein neues USB-C-Ladegerät vorgestellt, das auf Nutzer abzielt, die eine kompakte Ladelösung für unterwegs suchen, bei der das USB-C-Kabel bereits integriert ist.\r\nDas A… [+1832 chars]"
        },
        {
            "source": {
                "id": null,
                "name": "Ispazio.net"
            },
            "author": "Francesco Santagati",
            "title": "Successo per “F1: il Film” di Apple: oltre 500 milioni incassati",
            "description": "Successo per “F1: il Film” di Apple: oltre 500 milioni incassati\n\nIl film sulla Formula 1 targato Apple continua a dominare le sale cinematografiche. A un mese dal debutto ufficiale, il film ha ormai superato i 500 milioni di dollari di incasso al botteghino …",
            "url": "https://www.ispazio.net/2124027/film-f1-apple-500-milioni-box-office",
            "urlToImage": "https://www.ispazio.net/wp-content/uploads/2025/07/f1-the-movie-apple-record-insassi-ispazio.jpg",
            "publishedAt": "2025-07-28T09:08:26Z",
            "content": "Il film sulla Formula 1 targato Apple continua a dominare le sale cinematografiche. A un mese dal debutto ufficiale, il film ha ormai superato i 500 milioni di dollari di incasso al botteghino global… [+5155 chars]"
        },
        {
            "source": {
                "id": null,
                "name": "Ispazio.net"
            },
            "author": "Francesco Santagati",
            "title": "Blender arriverà su iPad Pro con interfaccia touch e supporto per la Apple Pencil",
            "description": "Blender arriverà su iPad Pro con interfaccia touch e supporto per la Apple Pencil\n\nBlender sta sviluppando una versione completamente nativa per iPad Pro, con pieno supporto per l’Apple Pencil Pro e un’interfaccia multitouch appositamente progettata per chi l…",
            "url": "https://www.ispazio.net/2124007/blender-ipad-pro-sviluppo",
            "urlToImage": "https://www.ispazio.net/wp-content/uploads/2025/07/blender-ipad-pro-ispazio.jpg",
            "publishedAt": "2025-07-28T08:11:40Z",
            "content": "Blender sta sviluppando una versione completamente nativa per iPad Pro, con pieno supporto per l’Apple Pencil Pro e un’interfaccia multitouch appositamente progettata per chi lavora su tablet.\r\nA con… [+5184 chars]"
        },
        {
            "source": {
                "id": null,
                "name": "Ispazio.net"
            },
            "author": "Francesco Santagati",
            "title": "iPhone 17 Pro, spuntano tre nuove possibili novità per la fotocamera",
            "description": "iPhone 17 Pro, spuntano tre nuove possibili novità per la fotocamera\n\nSecondo quanto riportato da MacRumors, Apple potrebbe introdurre tre importanti novità legate alla fotocamera con i futuri iPhone 17 Pro e 17 Pro Max. Le informazioni provengono da una font…",
            "url": "https://www.ispazio.net/2124013/iphone-17-pro-camera-novita-leak",
            "urlToImage": "https://www.ispazio.net/wp-content/uploads/2025/07/autonomia-iphone-17-pro-max-ispazio.jpg",
            "publishedAt": "2025-07-28T08:56:34Z",
            "content": "Secondo quanto riportato da MacRumors, Apple potrebbe introdurre tre importanti novità legate alla fotocamera con i futuri iPhone 17 Pro e 17 Pro Max. Le informazioni provengono da una fonte anonima … [+6024 chars]"
        },
        {
            "source": {
                "id": null,
                "name": "Yahoo Entertainment"
            },
            "author": "Rian Howlett",
            "title": "Stock market today: Dow, S&P 500, Nasdaq futures climb as Trump-EU trade deal kicks off huge week in markets",
            "description": "US stock futures climbed after a late Sunday announcement of a trade deal reached between the US and the EU.",
            "url": "https://finance.yahoo.com/news/live/stock-market-today-dow-sp-500-nasdaq-futures-climb-as-trump-eu-trade-deal-kicks-off-huge-week-in-markets-003043981.html",
            "urlToImage": "https://s.yimg.com/ny/api/res/1.2/3pyXeR.emyIrTe2f3.j8TA--/YXBwaWQ9aGlnaGxhbmRlcjt3PTEyMDA7aD04MDA-/https://s.yimg.com/os/creatr-uploaded-images/2025-07/f2796630-6ae6-11f0-bf7b-d0b8131038fd",
            "publishedAt": "2025-07-28T00:30:43Z",
            "content": "US stock futures edged higher Sunday evening as investors braced for a packed week featuring earnings from Big Tech heavyweights, a Federal Reserve meeting, inflation data, and President Trump's Aug.… [+2034 chars]"
        },
        {
            "source": {
                "id": null,
                "name": "Yahoo Entertainment"
            },
            "author": "AFP",
            "title": "Stock markets boosted after EU, US strike trade deal",
            "description": "Stock markets rose in Europe and Asia on Monday after the European Union and United States hammered out a deal to avert a potentially damaging trade war.News...",
            "url": "https://finance.yahoo.com/news/most-markets-rise-euro-boosted-030408282.html",
            "urlToImage": "https://media.zenfs.com/en/afp.com/629b479191568c25a8fd184dd7e511da",
            "publishedAt": "2025-07-28T07:37:20Z",
            "content": "European Commission President Ursula von der Leyen announced an EU-US trade deal with Donald Trump at his Scottish golf resort on Sunday (Brendan SMIALOWSKI)\r\nStock markets rose in Europe and Asia on… [+3937 chars]"
        },
        {
            "source": {
                "id": null,
                "name": "CHIP Online Deutschland"
            },
            "author": "Carina Blumenroth",
            "title": "Neue Leaks zum iPhone 17 Pro: Diese Features könnten Nutzer erwarten",
            "description": "Das neue iPhone 17 Pro soll mit der gesamten 17er-Reihe rund um den 9. September angekündigt werden. Aktuell gibt es Leaks mit Informationen zum neuen Smartphone.",
            "url": "https://www.chip.de/news/handy/neue-leaks-zum-iphone-17-pro-diese-features-koennten-nutzer-erwarten_c5c2e308-7d6f-4e08-84ad-c081b5c184da.html",
            "urlToImage": "https://quadro.burda-forward.de/ctf/6c054f2b-e3b4-4c82-bb99-76df0683c651.c2a15679-4a7d-446e-aa67-502ae050d11a.png?im=RegionOfInterestCrop%3D%281200%2C630%29%2CregionOfInterest%3D%28812%2C633%29&hash=899545c5623332af448bf7f5e9cc6092b801c253414ce6042b1d9c00c599707f",
            "publishedAt": "2025-07-28T09:16:00Z",
            "content": "Die neue iPhone-Generation rund um die 17er-Reihe wird noch in diesem Jahr veröffentlicht. Vorstellt werden die Modelle voraussichtlich in der Woche ab dem 9. September 2025, berichtet \"Macwelt\". All… [+2033 chars]"
        },
        {
            "source": {
                "id": null,
                "name": "Iphon.fr"
            },
            "author": "Pierre L. Duval",
            "title": "Récap : les 6 articles qu’il ne fallait pas manquer ces 7 derniers jours",
            "description": "iOS 26, iPhone 17 et iOS 18 ont fait la une de l’actualité ces derniers jours. Et sinon, quoi d’autre ?",
            "url": "https://www.iphon.fr/post/recapitulatif-top-articles-semaine-30-2025",
            "urlToImage": "https://www.iphon.fr/app/uploads/2025/06/apple-iphone-14-plus-1600x900.jpg",
            "publishedAt": "2025-07-28T06:48:03Z",
            "content": "Une nouvelle semaine riche en actualités Apple vient de se terminer. Aujourdhui est jour de reprise, mais aussi synonyme de bilan pour les sept jours passés. Certains dentre vous nont peut-être en ef… [+1311 chars]"
        },
        {
            "source": {
                "id": null,
                "name": "Iphon.fr"
            },
            "author": "Jean-Yves Alric",
            "title": "F1 le film : le pari fou d’Apple bat un nouveau record",
            "description": "Le géant de la Tech peut se réjouir.",
            "url": "https://www.iphon.fr/post/f1-le-film-le-pari-fou-dapple-bat-un-nouveau-record",
            "urlToImage": "https://www.iphon.fr/app/uploads/2025/03/F1-1500x900.jpg",
            "publishedAt": "2025-07-28T06:33:30Z",
            "content": "Cest un nouveau seuil fatidique pour le film F1 dApple. Daprès des sources du secteur citées par les médias américains, ce long-métrage est en effet sur le point de franchir les 500 millions de dolla… [+2121 chars]"
        },
        {
            "source": {
                "id": null,
                "name": "Iphon.fr"
            },
            "author": "Jason Filankembo",
            "title": "Fans de Severance, le clavier MDR Dasher est à réserver maintenant",
            "description": "Le réserver maintenant vous permet de faire une belle économie.",
            "url": "https://www.iphon.fr/post/fans-severance-clavier-mdr-dasher-reserver-maintenant",
            "urlToImage": "https://www.iphon.fr/app/uploads/2025/07/MDR-Dasher-clavier-1600x900.jpg",
            "publishedAt": "2025-07-28T07:54:10Z",
            "content": "Apple TV+ dispose de quelques séries iconiques dans son catalogue. Severance en fait incontestablement partie. Une bonne partie du public considère même la série comme le meilleur programme original … [+1711 chars]"
        },
        {
            "source": {
                "id": null,
                "name": "Iphon.fr"
            },
            "author": "Jason Filankembo",
            "title": "iPhone 17 Pro : leur application photo exclusive pourrait faire des jaloux",
            "description": "Une pluie d'innovations est attendue sur les iPhone 17 Pro.",
            "url": "https://www.iphon.fr/post/iphone-17-pro-application-photo-exclusive",
            "urlToImage": "https://www.iphon.fr/app/uploads/2025/07/iPhone-camera-1600x900.jpg",
            "publishedAt": "2025-07-28T07:03:58Z",
            "content": "La rentrée de septembre approche petit à petit. Oui, le constat est assez triste. Un peu moins pour les fans d’Apple, qui pourront se consoler avec le keynote et la présentation des nouveaux iPhone 1… [+1740 chars]"
        },
        {
            "source": {
                "id": null,
                "name": "Paul Tan's Automotive News"
            },
            "author": "Jonathan James Tan",
            "title": "Lexus NX 350h replaces NX 250 as entry-level NX in Malaysia – 2.5 hybrid, two-motor AWD, from RM396k",
            "description": "Visit Lexus Malaysia’s website and you’ll see a new NX variant – the Lexus NX 350h Luxury, priced from RM395,888. The RM371k NX 250 Luxury, which was the cheaper of the two launch variants in […]\nThe post Lexus NX 350h replaces NX 250 as entry-level NX in Mal…",
            "url": "https://paultan.org/2025/07/28/lexus-nx-350h-replaces-nx-250-as-entry-level-nx-in-malaysia-2-5-hybrid-two-motor-awd-from-rm396k/",
            "urlToImage": "https://paultan.org/image/2025/07/Lexus-NX-350h-Malaysia-hybrid-072025-1-1200x588.jpg",
            "publishedAt": "2025-07-28T07:42:23Z",
            "content": "Visit the Lexus Malaysia website and you’ll see a new NX variant – the Lexus NX 350h Luxury, priced from RM395,888. The RM371k NX 250 Luxury, which was the cheaper of the two launch variants in 2022 … [+2205 chars]"
        },
        {
            "source": {
                "id": null,
                "name": "Paul Tan's Automotive News"
            },
            "author": "Jonathan Lee",
            "title": "2025 Nissan X-Trail e-Power launched in Indonesia – 4th-gen finally in ASEAN, RM205k, Malaysia next?",
            "description": "We’ve been awaiting the arrival of the fourth-generation X-Trail ever since its North American counterpart, the Rogue, was revealed way back in 2020. And while Malaysians will have to wait a while more, the C-segment […]\nThe post 2025 Nissan X-Trail e-Power l…",
            "url": "https://paultan.org/2025/07/28/2025-nissan-x-trail-e-power-launched-in-indonesia-4th-gen-finally-in-asean-rm205k-malaysia-next/",
            "urlToImage": "https://paultan.org/image/2025/07/2025-GIIAS-Nissan-XTrail-1-1200x801.jpg",
            "publishedAt": "2025-07-28T02:43:54Z",
            "content": "We’ve been awaiting the arrival of the fourth-generation X-Trail ever since its North American counterpart, the Rogue, was revealed way back in 2020. And while Malaysians will have to wait a while mo… [+2691 chars]"
        },
        {
            "source": {
                "id": null,
                "name": "Paul Tan's Automotive News"
            },
            "author": "Jonathan Lee",
            "title": "2025 Honda HR-V 1.5 Turbo V facelift in Malaysia – full gallery of top petrol model with old lights, RM138k",
            "description": "When the facelifted Honda HR-V was launched two weeks ago, it was only shown in range-topping e:HEV RS trim, with no petrol variants present. Thankfully, Sumber Auto Edaran, a dealer in Section 13, Petaling Jaya, […]\nThe post 2025 Honda HR-V 1.5 Turbo V facel…",
            "url": "https://paultan.org/2025/07/28/2025-honda-hr-v-1-5-turbo-v-facelift-in-malaysia-full-gallery-of-top-petrol-model-with-old-lights-rm138k/",
            "urlToImage": "https://paultan.org/image/2025/07/2025-Honda-HRV-FL-V-Malaysia-Ext-26-1200x801.jpg",
            "publishedAt": "2025-07-28T09:13:43Z",
            "content": "When the facelifted Honda HR-V was launched two weeks ago, it was only shown in range-topping e:HEV RS trim, with no petrol variants present. Thankfully, Sumber Auto Edaran, a dealer in Section 13, P… [+8186 chars]"
        },
        {
            "source": {
                "id": null,
                "name": "ifun.de › Apple-News seit 2001"
            },
            "author": "Nicolas",
            "title": "Parachute Backup: Neue Mac-App sichert iCloud-Inhalte lokal",
            "description": "Mit Parachute Backup steht Mac-Nutzern seit wenigen Tagen eine neue Backup-Lösung zur Verfügung, die speziell für die Sicherung von iCloud-Inhalten konzipiert ist. Die Anwendung übernimmt automatisiert die Sicherung von iCloud-Fotos und Inhalten aus iCloud Dr…",
            "url": "https://www.ifun.de/parachute-backup-neue-mac-app-sichert-icloud-inhalte-lokal-261627/",
            "urlToImage": "https://images.ifun.de/wp-content/uploads/2025/07/parachute-feature.jpg",
            "publishedAt": "2025-07-28T05:54:47Z",
            "content": "Mit Parachute Backup steht Mac-Nutzern seit wenigen Tagen eine neue Backup-Lösung zur Verfügung, die speziell für die Sicherung von iCloud-Inhalten konzipiert ist. Die Anwendung übernimmt automatisie… [+1949 chars]"
        },
        {
            "source": {
                "id": null,
                "name": "Technews.tw"
            },
            "author": "Chen Kobe",
            "title": "iPhone 17 廣告後製泄密？新相機意外獲三項升級",
            "description": "距離新 iPhone 發表剩不到 2 個月，不意外地各種謠言滿天飛，最新消息則來自一個意外的來源：影片後製公司，他們在製作 iPhone 17 廣告時取得了一些提前曝光畫面，特別是新相機部分。 MacRumors 網站爆料者 Joe Rossignol 表示，他收到一個匿名消息，提供者表示新的 iP...",
            "url": "https://technews.tw/2025/07/28/iphone-17-pro-camera-rumor/",
            "urlToImage": "https://img.technews.tw/wp-content/uploads/2025/06/12113937/WWDC25-iOS-26-Camera.jpg",
            "publishedAt": "2025-07-28T02:17:50Z",
            "content": "iPhone 2 iPhone 17 \r\nMacRumors Joe Rossignol iPhone 17 Pro \r\n<ol><li> 5 8 </li><li> iPhone 17 Pro App</li><li> iPhone 17 Pro </li></ol> iPhone \r\n 4 YouTuber Jon Prosser iPhone iOS 26 Apple App Jon Pr… [+26 chars]"
        },
        {
            "source": {
                "id": null,
                "name": "Technews.tw"
            },
            "author": "蘇 子芸",
            "title": "蘋果傳評估採用 14A 製程，Intel 能翻身嗎?",
            "description": "蘋果正評估導入 Intel 最新 14A 製程技術，應用於未來 M 系列晶片，希望藉此打破長期依賴台積電單一代工的局面。 未來蘋果將推出許多自研產品，包括 iPhone A19、iPad、Apple Watch 和 Wi-Fi 晶片，目前皆由台積電代工。此次考慮導入 Intel 製程，被視為蘋果調整...",
            "url": "https://technews.tw/2025/07/28/apple-is-considering-using-intel-14a/",
            "urlToImage": "https://img.technews.tw/wp-content/uploads/2025/07/25080849/Intel-14A.jpg",
            "publishedAt": "2025-07-28T03:45:25Z",
            "content": "© 2013-2025 TechNews Inc. All rights reserved. | | | |"
        },
        {
            "source": {
                "id": null,
                "name": "heise online"
            },
            "author": "Wolfgang Kreutz",
            "title": "Tipp: Inhalte per iCloud teilen bei \"erweitertem Datenschutz\"",
            "description": "Apple erlaubt einen besseren Schutz für in iCloud gespeicherte Daten. Doch welche Auswirkungen hat das auf die Zusammenarbeit mit anderen?",
            "url": "https://www.heise.de/ratgeber/Tipp-Inhalte-per-iCloud-teilen-bei-erweitertem-Datenschutz-10500954.html",
            "urlToImage": "https://heise.cloudimg.io/bound/1200x1200/q85.png-lossy-85.webp-lossy-85.foil1/_www-heise-de_/imgs/18/4/9/0/4/5/3/3/apps-7ea8933c70afa5af.jpeg",
            "publishedAt": "2025-07-28T07:00:00Z",
            "content": "In Ihrem Artikel zum Thema iCloud-Sicherheit heben Sie die Ende-zu-Ende-Verschlüsselung \"Erweiterter Datenschutz\" hervor. Gilt der Schutz auch, wenn ich einzelne Dateien mit anderen Personen über iCl… [+2252 chars]"
        },
        {
            "source": {
                "id": null,
                "name": "heise online"
            },
            "author": "Malte Kirchner",
            "title": "heise+ | Liquid Glass: Apples neue Oberfläche für iOS 26, macOS 26 und Co. im Detail",
            "description": "iPhone, iPad, Mac, Watch – jedes Apple-Gerät bekommt mit den Systemen im Herbst eine neue Bedienoberfläche. Was kann sie und was sagen Designer und Entwickler?",
            "url": "https://www.heise.de/hintergrund/Liquid-Glass-Apples-neue-Oberflaeche-fuer-iOS-26-macOS-26-und-Co-im-Detail-10487350.html",
            "urlToImage": "https://heise.cloudimg.io/bound/1200x1200/q85.png-lossy-85.webp-lossy-85.foil1/_www-heise-de_/imgs/18/4/8/9/7/4/7/2/apple_liquid_glas_lbe_aufmacher_3-ce91416576cea492.jpg",
            "publishedAt": "2025-07-28T06:00:00Z",
            "content": "Inhaltsverzeichnis\r\nApple macht den Blick in die Glaskugel zum neuen Standard. Genauer gesagt ist es die Sicht durch Glaslinsen, die ab iOS 26 auf dem iPhone und in den neuen Betriebssystemversionen … [+1035 chars]"
        },
        {
            "source": {
                "id": null,
                "name": "heise online"
            },
            "author": "Ben Schwan",
            "title": "iOS 26: Auch iPhone-11-User dürften nun mittesten",
            "description": "Aufgrund von technischen Problemen durften Nutzer des ältesten von iOS 26 unterstützten iPhones kurzzeitig nicht mittesten. Jetzt dürfen sie.",
            "url": "https://www.heise.de/news/iOS-26-Auch-iPhone-11-User-duerften-nun-mittesten-10501030.html",
            "urlToImage": "https://heise.cloudimg.io/bound/1200x1200/q85.png-lossy-85.webp-lossy-85.foil1/_www-heise-de_/imgs/18/4/9/0/4/5/7/4/iphone-11-eb608f421fcb871e.jpg",
            "publishedAt": "2025-07-28T08:16:00Z",
            "content": "close notice\r\nThis article is also available in\r\n English.\r\nIt was translated with technical assistance and editorially reviewed before publication.\r\nDont show this again.\r\nSeit letzter Woche ist es … [+2299 chars]"
        },
        {
            "source": {
                "id": null,
                "name": "NPR"
            },
            "author": "Wailin Wong",
            "title": "A baby bonds bonanza",
            "description": "Baby bond fever is catching on. In recent years, states like Connecticut have been experimenting with giving newborns government-seeded accounts that grow tax-free until they are 18. Now, President Trump's signature tax and spending bill will give a thousand …",
            "url": "https://www.npr.org/2025/07/28/1256346019/can-baby-bonds-close-wealth-gap",
            "urlToImage": "https://media.npr.org/assets/img/2025/07/25/art-as-well_wide-b0ba71d93d35ee5f0c9bef89d2144a2f64887312.jpg?s=1400&c=100&f=jpeg",
            "publishedAt": "2025-07-28T07:00:59Z",
            "content": "Baby bond fever is catching on. In recent years, states like Connecticut have been experimenting with giving newborns government-seeded accounts that grow tax-free until they are 18. Now, President T… [+578 chars]"
        },
        {
            "source": {
                "id": null,
                "name": "Geeky Gadgets"
            },
            "author": "Roland Hutchinson",
            "title": "Apple Re-Released iOS 26 Beta 4: Here’s What Changed!",
            "description": "Apple has officially re-released iOS 26 Beta 4, aligning its build number and features with the iOS 26 Public Beta 1. Identified by build number 23A5297M, this update focuses on addressing bugs, enhancing performance, and introducing minor feature refinements…",
            "url": "https://www.geeky-gadgets.com/re-released-ios-26-beta-4/",
            "urlToImage": "https://www.geeky-gadgets.com/wp-content/uploads/2025/07/ios-26-beta-4-performance-improvements_optimized.jpg",
            "publishedAt": "2025-07-28T06:00:03Z",
            "content": "Apple has officially re-released iOS 26 Beta 4, aligning its build number and features with the iOS 26 Public Beta 1. Identified by build number 23A5297M, this update focuses on addressing bugs, enha… [+5364 chars]"
        },
        {
            "source": {
                "id": null,
                "name": "Geeky Gadgets"
            },
            "author": "Julian Horsey",
            "title": "Use Apple Notes to Simplify Your Life : Ditch the Overwhelm & Paid Apps",
            "description": "Have you ever felt overwhelmed by the sheer number of apps promising to organize your life, only to find yourself juggling between them? In a world saturated with feature-packed productivity tools, it’s easy to overlook the power of simplicity. Enter Apple No…",
            "url": "https://www.geeky-gadgets.com/organizing-your-life-with-apple-notes/",
            "urlToImage": "https://www.geeky-gadgets.com/wp-content/uploads/2025/07/apple-notes-productivity-tips_optimized-1.jpg",
            "publishedAt": "2025-07-28T08:17:09Z",
            "content": "Have you ever felt overwhelmed by the sheer number of apps promising to organize your life, only to find yourself juggling between them? In a world saturated with feature-packed productivity tools, i… [+7031 chars]"
        },
        {
            "source": {
                "id": null,
                "name": "Geeky Gadgets"
            },
            "author": "Roland Hutchinson",
            "title": "Get iOS 26 Public Beta Today! Quick & Simple Install",
            "description": "The release of the iOS 26 public beta provides users with an early opportunity to explore Apple’s latest software updates. This version introduces a variety of new features and design improvements, offering a glimpse into the future of iOS. However, as with a…",
            "url": "https://www.geeky-gadgets.com/get-ios-26-public-beta/",
            "urlToImage": "https://www.geeky-gadgets.com/wp-content/uploads/2025/07/ios-26-beta-installation-guide_optimized.jpg",
            "publishedAt": "2025-07-28T08:00:01Z",
            "content": "The release of the iOS 26 public beta provides users with an early opportunity to explore Apples latest software updates. This version introduces a variety of new features and design improvements, of… [+5831 chars]"
        },
        {
            "source": {
                "id": null,
                "name": "Geeky Gadgets"
            },
            "author": "Roland Hutchinson",
            "title": "iOS 26 Public Beta is LIVE! Do These 10 Things FIRST",
            "description": "Apple has officially launched the iOS 26 public beta, unveiling a wide array of features aimed at enhancing usability, customization, and overall efficiency. This update introduces a fresh visual identity, smarter tools, and advanced functionality across apps…",
            "url": "https://www.geeky-gadgets.com/ios-26-public-beta-features-2/",
            "urlToImage": "https://www.geeky-gadgets.com/wp-content/uploads/2025/07/ios-26-liquid-glass-design-update_optimized-1.jpg",
            "publishedAt": "2025-07-28T07:30:53Z",
            "content": "Apple has officially launched the iOS 26 public beta, unveiling a wide array of features aimed at enhancing usability, customization, and overall efficiency. This update introduces a fresh visual ide… [+6837 chars]"
        },
        {
            "source": {
                "id": null,
                "name": "Geeky Gadgets"
            },
            "author": "Roland Hutchinson",
            "title": "Your iPhone Can Do THIS?! 10 Brilliant Things to Try NOW!",
            "description": "Your iPhone is more than just a device for calls and texts—it’s a versatile tool packed with features designed to enhance your daily life. While many users are familiar with its basic functions, there are several lesser-known features that can significantly i…",
            "url": "https://www.geeky-gadgets.com/your-iphone-can-do-this-10-brilliant-things-to-try-now/",
            "urlToImage": "https://www.geeky-gadgets.com/wp-content/uploads/2025/07/hidden-iphone-features-guide_optimized-1.jpg",
            "publishedAt": "2025-07-28T07:00:58Z",
            "content": "Your iPhone is more than just a device for calls and textsits a versatile tool packed with features designed to enhance your daily life. While many users are familiar with its basic functions, there … [+5445 chars]"
        },
        {
            "source": {
                "id": null,
                "name": "Ixbt.com"
            },
            "author": "jin@ixbt.com (Jin)",
            "title": "В Россию прибыла партия новейших Volkswagen Tiguan. Есть бензиновые и дизельные версии, R-Line и Tiguan Allspace",
            "description": "На российский рынок поступила партия кроссоверов третьего поколения Volkswagen Tiguan, о которой сообщалось ещё неделю назад. Модели доступны в различных версиях, включая гибридные варианты. Базовая версия Tiguan с бензиновым двигателем 1.5 TSI мощностью 150 …",
            "url": "https://www.ixbt.com/news/2025/07/28/volkswagen-tiguan-r-line-tiguan-allspace.html",
            "urlToImage": "https://www.ixbt.com/img/n1/news/2025/6/1/neu-tiguan-nf-tn2503-v1_large.jpg",
            "publishedAt": "2025-07-28T02:49:00Z",
            "content": "Volkswagen Tiguan, .  , .\r\n Tiguan 1.5 TSI 150 .., , 6 . , Android Auto Apple CarPlay, .\r\n R-Line , 129 , 9 , , .\r\n - R-Line 193 .. , 9 , Tiguan Allspace 8,4 ."
        },
        {
            "source": {
                "id": null,
                "name": "NPR"
            },
            "author": "Berly McCoy",
            "title": "How the largest daily migration on Earth stores carbon in the ocean",
            "description": "The twilight zone of the ocean is a mysterious place. At 200-1000 meters below the surface, it's a tough place to study. That's why, during World War II, people reading sonograms from this zone were perplexed when it looked as if the ocean floor was moving up…",
            "url": "https://www.npr.org/2025/07/28/1256346011/ocean-twilight-zone-largest-migration-carbon",
            "urlToImage": "https://media.npr.org/assets/img/2025/07/25/swscep4_wide-0241f58d40e5fae5b9152598f465ff25b9f0b517.jpg?s=1400&c=100&f=jpeg",
            "publishedAt": "2025-07-28T07:00:59Z",
            "content": "Lanternfish are one of the many residents of the ocean's twilight zone, which is known for being very dark and housing likely the majority of the sea's fish.\r\n3dsam79/Getty Images\r\nThe twilight zone … [+958 chars]"
        },
        {
            "source": {
                "id": null,
                "name": "Erickimphotography.com"
            },
            "author": "ERIC KIM",
            "title": "It seems futile to try to beat the best?",
            "description": "So for example, in Asia, grab is like by far the most dominant. All of these competitors trying to grab market chair seems like a waste of time. Also, ABA ABA PAY here is like a gazillion fold the dominant payment portal. All these other second-tier banks, tr…",
            "url": "https://erickimphotography.com/blog/2025/07/27/it-seems-futile-to-try-to-beat-the-best-2/",
            "urlToImage": null,
            "publishedAt": "2025-07-28T00:18:54Z",
            "content": "So for example, in Asia, grab is like by far the most dominant. All of these competitors trying to grab market chair seems like a waste of time.\r\nAlso, ABA ABA PAY here is like a gazillion fold the d… [+1786 chars]"
        },
        {
            "source": {
                "id": null,
                "name": "mobiFlip.de"
            },
            "author": "Oliver Schwuchow",
            "title": "Apple iPhone 17 Pro: Neuer Kamera-Leak klingt sehr unwahrscheinlich",
            "description": "Das iPhone 17 Pro wird einige Optimierungen bei der Kamera mitbringen, das steht bisher schon im Raum und das behauptet auch eine Quelle, die MacRumors drei Neuerungen verraten hat, die […]",
            "url": "https://www.mobiflip.de/apple-iphone-17-pro-neuer-kamera-leak-klingt-sehr-unwahrscheinlich/",
            "urlToImage": "https://www.mobiflip.de/wp-content/uploads/2025/07/apple-iphone-17-pro-blau-mockup.jpg",
            "publishedAt": "2025-07-28T03:32:14Z",
            "content": "Das iPhone 17 Pro wird einige Optimierungen bei der Kamera mitbringen, das steht bisher schon im Raum und das behauptet auch eine Quelle, die MacRumors drei Neuerungen verraten hat, die wir so bisher… [+928 chars]"
        },
        {
            "source": {
                "id": null,
                "name": "mobiFlip.de"
            },
            "author": "René Hesse",
            "title": "Disney+ überholt Netflix in mehreren Kategorien",
            "description": "Laut der aktuellen „Simon-Kucher Streaming-Studie 2025“ kommt es zu Verschiebungen auf dem deutschen Streamingmarkt. Disney+ erreicht in diesem Jahr erstmals die Spitzenposition in mehreren inhaltlichen Kategorien, darunter „Exklusive Inhalte“ und […]",
            "url": "https://www.mobiflip.de/disney-ueberholt-netflix-in-mehreren-kategorien/",
            "urlToImage": "https://www.mobiflip.de/wp-content/uploads/2022/11/amazon-fire-tv-remote-pro-tasten.jpg",
            "publishedAt": "2025-07-28T07:16:44Z",
            "content": "Laut der aktuellen Simon-Kucher Streaming-Studie 2025 kommt es zu Verschiebungen auf dem deutschen Streamingmarkt.\r\nDisney+ erreicht in diesem Jahr erstmals die Spitzenposition in mehreren inhaltlich… [+1786 chars]"
        },
        {
            "source": {
                "id": null,
                "name": "Maclife.de"
            },
            "author": "Paul Schneider",
            "title": "iPhone 17 Pro: Gerüchte um 8x Zoom, Pro-Kamera-App und zweiten Camera Control-Button",
            "description": "Ein anonymer Informant will Details zu drei neuen Kamera-Features der iPhone 17 Pro-Modelle kennen – darunter achtfacher optischer Zoom. (Weiterlesen)",
            "url": "https://www.maclife.de/news/iphone-17-pro-8x-zoom-pro-kamera-app-geplant-100125961.html",
            "urlToImage": "https://www.maclife.de/media/maclife/styles/tec_frontend_opengraph/public/images/editors/2025_31/image-125961--4616981.jpg?itok=cbW3Kv5U",
            "publishedAt": "2025-07-28T09:01:34Z",
            "content": "Ein anonymer Informant hat neue Details zu den iPhone 17 Pro-Modellen geteilt, die einige überraschende Kamera-Features versprechen. Die Gerüchte stammen von einem Tippgeber, der behauptet, Einblicke… [+3698 chars]"
        },
        {
            "source": {
                "id": null,
                "name": "Maclife.de"
            },
            "author": "Jan Tissler",
            "title": "9 Funktionen der iPhone-Kamera für bessere Fotos erklärt",
            "description": "Nicht nur die Hardware der iPhone-Kamera ist über die Jahre immer besser geworden, sondern auch die Software. Sie hilft dir mit schlauen Automatiken und Algorithmen, das meiste aus deinen Motiven herauszuholen. In diesem Artikel zeige ich dir, welche Features…",
            "url": "https://www.maclife.de/news/9-funktionen-iphone-kamera-bessere-fotos-erklaert-100125940.html",
            "urlToImage": "https://www.maclife.de/media/maclife/styles/tec_frontend_opengraph/public/images/editors/2025_30/image-125940--4616926.jpg?itok=-VP7hVCW",
            "publishedAt": "2025-07-28T05:43:02Z",
            "content": "Der Porträtmodus: Professioneller Look per Klick\r\nDer Porträtmodus ist eine der beliebtesten Funktionen der iPhone-Kamera. Er simuliert den Look, den man sonst nur mit teuren Kameras und lichtstarken… [+9316 chars]"
        },
        {
            "source": {
                "id": null,
                "name": "Maclife.de"
            },
            "author": "Jan Tissler",
            "title": "Den Mond mit dem iPhone fotografieren: So klappt’s besser",
            "description": "Du kennst das: Der Vollmond steht beeindruckend am Himmel, du willst diesen sagenhaften Moment mit deiner leistungsfähigen iPhone-Kamera festhalten und … das Ergebnis ist ein unscharfer weißer Blob im Nichts. Warum das so ist und wie es besser geht, erklären …",
            "url": "https://www.maclife.de/news/mond-iphone-fotografieren-klappts-besser-100125944.html",
            "urlToImage": "https://www.maclife.de/media/maclife/styles/tec_frontend_opengraph/public/images/editors/2025_30/image-125944--4616914.jpg?itok=cIh44AIB",
            "publishedAt": "2025-07-28T07:53:22Z",
            "content": "Warum Mondfotos oft enttäuschen\r\nDass Mondfotos oft so nichtssagend sind, hat mit mehreren Dingen zu tun. Als erstes spielt uns das eigene Gehirn einen Streich: Starren wir auf den majestätischen Mon… [+9423 chars]"
        },
        {
            "source": {
                "id": null,
                "name": "Toodaylab.com"
            },
            "author": "吴诗源",
            "title": "即将要在深圳开出又一家 Apple Store 的苹果，要准备关掉大连首店了",
            "description": "7 月 25 日，苹果正式确认了位于深圳前海壹方城的全新零售店，新店将在 8 月 16 日上午 10 点正式开幕。店铺在打围阶段还没挂苹果 logo 的时候就已经被“果粉”们发现，而这将成为深圳第三家 Apple Store（前两家分别在深圳万象城和益田假日广场）。这样深圳的店铺数量将超过有两家的广州。苹果官网已经上线了店铺页面，不过或许是店铺规格不高，这次没有专门的新闻稿，除了一个“这方来逐浪”的 slogan，包括预热 logo 都是一个通用 logo，这个 logo 已经出现在多家店铺开业前的预热中了，一些…",
            "url": "https://www.toodaylab.com/83617",
            "urlToImage": null,
            "publishedAt": "2025-07-28T06:05:42Z",
            "content": "7 25 8 16 10 \r\n logo Apple Store\r\nZARA ZARA 4 24 2300 \r\nslogan logo logo logo \r\nApple Store 8 9 8 \r\n 5 \r\n2015 10 24 Apple Store 10 Apple Store2016 3 19 \r\n2027 Apple Store \r\n2022"
        }
    ]
}